Workbook

Sheet 周度明细
A1: 青屿茶研 市场部 · 2026年7月 渠道曝光与线索数据（周度明细）
A2: 统计周期：2026年7月1日 至 2026年7月31日 ｜ 转化率 = 有效线索数量 ÷ 线索数量 × 100%
A3: ⚠️ 本项目中的品牌、人员、部门、活动、数据和文件均为虚构，仅用于教学演示，与任何真实企业无关。
A5: 渠道 | B5: 统计周 | C5: 日期范围 | D5: 曝光量 | E5: 线索数量 | F5: 有效线索
A6: 小红书 | B6: W1 | C6: 07-01 ~ 07-07 | D6: 32000 | E6: 210 | F6: 71
A7: 小红书 | B7: W2 | C7: 07-08 ~ 07-14 | D7: 58000 | E7: 402 | F7: 137
A8: 小红书 | B8: W3 | C8: 07-15 ~ 07-21 | D8: 49000 | E8: 348 | F8: 118
A9: 小红书 | B9: W4 | C9: 07-22 ~ 07-31 | D9: 46000 | E9: 320 | F9: 110
A10: 抖音 | B10: W1 | C10: 07-01 ~ 07-07 | D10: 48000 | E10: 280 | F10: 70
A11: 抖音 | B11: W2 | C11: 07-08 ~ 07-14 | D11: 72000 | E11: 430 | F11: 108
A12: 抖音 | B12: W3 | C12: 07-15 ~ 07-21 | D12: 78000 | E12: 460 | F12: 115
A13: 抖音 | B13: W4 | C13: 07-22 ~ 07-31 | D13: 64000 | E13: 390 | F13: 97
A14: 微信公众号 | B14: W1 | C14: 07-01 ~ 07-07 | D14: 12000 | E14: 130 | F14: 58
A15: 微信公众号 | B15: W2 | C15: 07-08 ~ 07-14 | D15: 16000 | E15: 170 | F15: 77
A16: 微信公众号 | B16: W3 | C16: 07-15 ~ 07-21 | D16: 15000 | E16: 160 | F16: 72
A17: 微信公众号 | B17: W4 | C17: 07-22 ~ 07-31 | D17: 15000 | E17: 160 | F17: 72
... A25: 线下门店 | B25: W4 | C25: 07-22 ~ 07-31 | D25: 11000 | E25: 175 | F25: 79
A27: 全渠道合计 | D27: =SUM(D6:D25) | E27: =SUM(E6:E25) | F27: =SUM(F6:F25)

Sheet 渠道汇总
A1: 青屿茶研 市场部 · 2026年7月 渠道汇总
A2: 统计周期：2026年7月1日 至 2026年7月31日 ｜ 转化率 = 有效线索数量 ÷ 线索数量 × 100%
A3: 本表所有数值均由「周度明细」工作表通过 SUMIF 公式计算得出，未手工填写。
A5: 渠道 | B5: 曝光量 | C5: 线索数量 | D5: 有效线索 | E5: 转化率 | F5: 曝光量占比 | G5: 有效线索占比
A6: 小红书 | B6: =SUMIF(周度明细!$A$6:$A$25,$A6,周度明细!$D$6:$D$25) | C6: =SUMIF(周度明细!$A$6:$A$25,$A6,周度明细!$E$6:$E$25) | D6: =SUMIF(周度明细!$A$6:$A$25,$A6,周度明细!$F$6:$F$25) | E6: =D6/C6 | F6: =B6/$B$11 | G6: =D6/$D$11
A7: 抖音 | B7: =SUMIF(周度明细!$A$6:$A$25,$A7,周度明细!$D$6:$D$25) | C7: =SUMIF(周度明细!$A$6:$A$25,$A7,周度明细!$E$6:$E$25) | D7: =SUMIF(周度明细!$A$6:$A$25,$A7,周度明细!$F$6:$F$25) | E7: =D7/C7 | F7: =B7/$B$11 | G7: =D7/$D$11
A8: 微信公众号 | B8: =SUMIF(周度明细!$A$6:$A$25,$A8,周度明细!$D$6:$D$25) | C8: =SUMIF(周度明细!$A$6:$A$25,$A8,周度明细!$E$6:$E$25) | D8: =SUMIF(周度明细!$A$6:$A$25,$A8,周度明细!$F$6:$F$25) | E8: =D8/C8 | F8: =B8/$B$11 | G8: =D8/$D$11
A9: 微信社群 | B9: =SUMIF(周度明细!$A$6:$A$25,$A9,周度明细!$D$6:$D$25) | C9: =SUMIF(周度明细!$A$6:$A$25,$A9,周度明细!$E$6:$E$25) | D9: =SUMIF(周度明细!$A$6:$A$25,$A9,周度明细!$F$6:$F$25) | E9: =D9/C9 | F9: =B9/$B$11 | G9: =D9/$D$11
A10: 线下门店 | B10: =SUMIF(周度明细!$A$6:$A$25,$A10,周度明细!$D$6:$D$25) | C10: =SUMIF(周度明细!$A$6:$A$25,$A10,周度明细!$E$6:$E$25) | D10: =SUMIF(周度明细!$A$6:$A$25,$A10,周度明细!$F$6:$F$25) | E10: =D10/C10 | F10: =B10/$B$11 | G10: =D10/$D$11
A11: 合计 | B11: =SUM(B6:B10) | C11: =SUM(C6:C10) | D11: =SUM(D6:D10) | E11: =D11/C11 | F11: 100.0% | G11: 100.0%
A13: ⚠️ 注意：整体转化率 = 有效线索合计 ÷ 线索合计，不是五个渠道转化率的算术平均值。两者结果不同。
A14: 正确算法：=D11/C11 错误算法：=AVERAGE(E6:E10) （两者相差约 4.8 个百分点）

Sheet 数据字典
A1: 数据字典与计算口径
A3: 字段 | B3: 定义 | C3: 单位 | D3: 来源 / 计算方式
A4: 渠道 | B4: 本月投放或运营的对外触点 | C4: — | D4: 固定 5 个：小红书、抖音、微信公众号、微信社群、线下门店
A5: 统计周 | B5: 自然周划分，W4 含 7/29–7/31 共 10 天 | C5: — | D5: W1 07-01~07-07；W2 07-08~07-14；W3 07-15~07-21；W4 07-22~07-31
A6: 曝光量 | B6: 内容被展示的次数（去重前） | C6: 次 | D6: 各渠道后台导出
A7: 线索数量 | B7: 留下联系方式或完成互动动作的用户数 | C7: 条 | D7: 各渠道后台导出
A8: 有效线索 | B8: 经人工初筛，符合目标客群且联系方式可用的线索 | C8: 条 | D8: 人工筛选后统计
A9: 转化率 | B9: 有效线索占全部线索的比例 | C9: % | D9: 有效线索数量 ÷ 线索数量 × 100%
A10: 整体转化率 | B10: 全渠道汇总口径的转化率 | C10: % | D10: 有效线索合计 ÷ 线索合计 × 100%（非各渠道转化率的平均值）
A11: 曝光量占比 | B11: 单渠道曝光量占全渠道曝光量的比例 | C11: % | D11: 单渠道曝光量 ÷ 全渠道曝光量合计
A12: 有效线索占比 | B12: 单渠道有效线索占全渠道有效线索的比例 | C12: % | D12: 单渠道有效线索 ÷ 全渠道有效线索合计
A14: 本表不含预算、成本、客单价、销售额、用户画像数据。任何涉及上述内容的分析结论均无数据支撑。
